CHANGES.txt
README.txt
resurrect.c
setup.cfg
setup.py
docs/HISTORY.txt
z3c/__init__.py
z3c.memhunt.objgraph.egg-info/PKG-INFO
z3c.memhunt.objgraph.egg-info/SOURCES.txt
z3c.memhunt.objgraph.egg-info/dependency_links.txt
z3c.memhunt.objgraph.egg-info/namespace_packages.txt
z3c.memhunt.objgraph.egg-info/not-zip-safe
z3c.memhunt.objgraph.egg-info/requires.txt
z3c.memhunt.objgraph.egg-info/top_level.txt
z3c/memhunt/__init__.py
z3c/memhunt/objgraph/README.txt
z3c/memhunt/objgraph/__init__.py
z3c/memhunt/objgraph/configure.zcml
z3c/memhunt/objgraph/tests.py
z3c/memhunt/objgraph/version.txt
z3c/memhunt/objgraph/browser/__init__.py
z3c/memhunt/objgraph/browser/configure.zcml
z3c/memhunt/objgraph/browser/configure_zope2.zcml
z3c/memhunt/objgraph/browser/configure_zope3.zcml
z3c/memhunt/objgraph/browser/views.py
z3c/memhunt/objgraph/browser/resources/keep.txt
z3c/memhunt/objgraph/browser/resources/history/keep.txt
z3c/memhunt/objgraph/browser/zpt/debug.css
z3c/memhunt/objgraph/browser/zpt/ref_common_count.pt
z3c/memhunt/objgraph/browser/zpt/ref_count.pt
z3c/memhunt/objgraph/browser/zpt/start.pt