Metadata-Version: 1.0
Name: z3c.memhunt.objgraph
Version: 0.1dev-r118724
Summary: UNKNOWN
Home-page: ''
Author: Daniel Blackburn & Holmes Corporation
Author-email: danielb@holmescorp.com
License: ZPL 2.1
Keywords: zope zope2 zope3 memory objgraph graphviz guppy
Platform: UNKNOWN
Classifier: Development Status :: 4 - Beta
Classifier: Environment :: Web Environment
Classifier: Intended Audience :: Developers
Classifier: License :: OSI Approved :: Zope Public License
Classifier: Programming Language :: Python
Classifier: Natural Language :: English
Classifier: Operating System :: OS Independent
Classifier: Topic :: Internet :: WWW/HTTP
Classifier: Framework :: Zope3
